README.md
setup.py
carvpath/__init__.py
carvpath.egg-info/PKG-INFO
carvpath.egg-info/SOURCES.txt
carvpath.egg-info/dependency_links.txt
carvpath.egg-info/top_level.txt